{
  "db_name": "PostgreSQL",
  "query": "\n        SELECT\n            COUNT(*) FILTER (WHERE value = 'FILLER')         AS \"filler!\",\n            COUNT(*) FILTER (WHERE value = 'WORTH_WATCHING') AS \"worth_watching!\",\n            COUNT(*) FILTER (WHERE value = 'CANON')          AS \"canon!\"\n        FROM vote WHERE episode_id = $1\n        ",
  "describe": {
    "columns": [
      {
        "ordinal": 0,
        "name": "filler!",
        "type_info": "Int8"
      },
      {
        "ordinal": 1,
        "name": "worth_watching!",
        "type_info": "Int8"
      },
      {
        "ordinal": 2,
        "name": "canon!",
        "type_info": "Int8"
      }
    ],
    "parameters": {
      "Left": [
        "Uuid"
      ]
    },
    "nullable": [
      null,
      null,
      null
    ]
  },
  "hash": "40656c36ccd85e190f9d514b8a0155193c354bc33f86b05dd92fc5a072d3c496"
}
