{
  "db_name": "PostgreSQL",
  "query": "\n        INSERT INTO episode (\n            show_id, season_id, tmdb_id, season_number, episode_number,\n            name, overview, air_date, still_path, tmdb_vote_average, tmdb_vote_count\n        )\n        SELECT $1, $2, e.tmdb_id, e.season_number, e.episode_number, e.name, e.overview,\n               e.air_date, e.still_path, e.tmdb_vote_average, e.tmdb_vote_count\n        FROM jsonb_to_recordset($3) AS e(\n            tmdb_id bigint, season_number int, episode_number int, name text,\n            overview text, air_date date, still_path text,\n            tmdb_vote_average float8, tmdb_vote_count int\n        )\n        ON CONFLICT (tmdb_id) DO UPDATE SET\n            name = EXCLUDED.name,\n            overview = EXCLUDED.overview,\n            air_date = EXCLUDED.air_date,\n            still_path = EXCLUDED.still_path,\n            tmdb_vote_average = EXCLUDED.tmdb_vote_average,\n            tmdb_vote_count = EXCLUDED.tmdb_vote_count\n        ",
  "describe": {
    "columns": [],
    "parameters": {
      "Left": [
        "Uuid",
        "Uuid",
        "Jsonb"
      ]
    },
    "nullable": []
  },
  "hash": "ef10d635234f1253555309ad05601e91a9b904d13ebaa2c441de90496ab70856"
}
